MANIFEST.in
README.md
requirements.txt
setup.py
traxix.trixli.egg-info/PKG-INFO
traxix.trixli.egg-info/SOURCES.txt
traxix.trixli.egg-info/dependency_links.txt
traxix.trixli.egg-info/requires.txt
traxix.trixli.egg-info/top_level.txt
traxix/trixli/__init__.py
traxix/trixli/again
traxix/trixli/ansi.py
traxix/trixli/b64
traxix/trixli/ec2l
traxix/trixli/f
traxix/trixli/fe
traxix/trixli/fp
traxix/trixli/fr
traxix/trixli/fython
traxix/trixli/pexor.py
traxix/trixli/utils.py