Metadata-Version: 2.1
Name: traxix.trixli
Version: 0.1.0
Summary: UNKNOWN
Home-page: https://gitlab.com/trax/trixli
Author: trax Omar Givernaud
License: UNKNOWN
Platform: UNKNOWN
